YesssSMS/CLI.py
YesssSMS/__init__.py
YesssSMS/api.py
YesssSMS/const.py
YesssSMS/version.json
YesssSMS-0.8.1.dist-info/LICENSE.txt
YesssSMS-0.8.1.dist-info/METADATA
YesssSMS-0.8.1.dist-info/WHEEL
YesssSMS-0.8.1.dist-info/entry_points.txt
YesssSMS-0.8.1.dist-info/top_level.txt
YesssSMS-0.8.1.dist-info/RECORD
