Metadata-Version: 2.1
Name: YesssSMS
Version: 0.8.1
Summary: YesssSMS let's you send SMS via yesss.at's website.
Home-page: https://gitlab.com/flowolf/yessssms
Author: Florian Klien
Author-email: flowolf@klienux.org
License: MIT
Keywords: SMS,Yesss,messaging
Platform: any
Classifier: Development Status :: 5 - Production/Stable
Classifier: Environment :: Console
Classifier: Intended Audience :: Developers
Classifier: Intended Audience :: System Administrators
Classifier: Topic :: Communications :: Telephony
Classifier: License :: OSI Approved :: MIT License
Classifier: Programming Language :: Python :: 3
Requires-Python: >=3.8
License-File: LICENSE.txt
Requires-Dist: requests
Requires-Dist: beautifulsoup4
